MANIFEST.in
README.md
setup.py
src/aircraft/__init__.py
src/aircraft/validators.py
src/aircraft.egg-info/PKG-INFO
src/aircraft.egg-info/SOURCES.txt
src/aircraft.egg-info/dependency_links.txt
src/aircraft.egg-info/entry_points.txt
src/aircraft.egg-info/requires.txt
src/aircraft.egg-info/top_level.txt
src/aircraft/cli/__init__.py
src/aircraft/cli/main.py
src/aircraft/deploys/__init__.py
src/aircraft/deploys/edge_os/__init__.py
src/aircraft/deploys/edge_os/dhcp.py
src/aircraft/deploys/edge_os/models/__init__.py
src/aircraft/deploys/edge_os/models/v1beta3/__init__.py
src/aircraft/deploys/edge_os/models/v1beta3/dhcp_data.py
src/aircraft/deploys/edge_os/templates/dhcp-configure.sh.j2
src/aircraft/deploys/edge_os/templates/dhcp-disable.sh.j2
src/aircraft/deploys/synology/__init__.py
src/aircraft/deploys/synology/pxe.py
src/aircraft/deploys/synology/models/__init__.py
src/aircraft/deploys/synology/models/v1beta3/__init__.py
src/aircraft/deploys/ubuntu/__init__.py
src/aircraft/deploys/ubuntu/apache2.py
src/aircraft/deploys/ubuntu/dnsmasq.py
src/aircraft/deploys/ubuntu/pxe.py
src/aircraft/deploys/ubuntu/models/__init__.py
src/aircraft/deploys/ubuntu/models/v1beta3/__init__.py
src/aircraft/deploys/ubuntu/models/v1beta3/base_model.py
src/aircraft/deploys/ubuntu/models/v1beta3/bootfile_data.py
src/aircraft/deploys/ubuntu/models/v1beta3/dhcp_data.py
src/aircraft/deploys/ubuntu/models/v1beta3/dns_data.py
src/aircraft/deploys/ubuntu/models/v1beta3/dnsmasq_data.py
src/aircraft/deploys/ubuntu/models/v1beta3/http_data.py
src/aircraft/deploys/ubuntu/models/v1beta3/machine_data.py
src/aircraft/deploys/ubuntu/models/v1beta3/network_config_data.py
src/aircraft/deploys/ubuntu/models/v1beta3/pxe_data.py
src/aircraft/deploys/ubuntu/models/v1beta3/storage_config_data.py
src/aircraft/deploys/ubuntu/models/v1beta3/tftp_data.py
src/aircraft/deploys/ubuntu/templates/apache2-directory.conf.j2
src/aircraft/deploys/ubuntu/templates/current-installer.j2
src/aircraft/deploys/ubuntu/templates/dnsmasq.conf.j2
src/aircraft/deploys/ubuntu/templates/grub2.autoinstall-v1.cfg.j2
src/aircraft/deploys/ubuntu/templates/grub2.legacy-netboot.cfg.j2
src/aircraft/deploys/ubuntu/templates/legacy-preseed-auto.seed.j2
