Metadata-Version: 2.1
Name: aircraft
Version: 0.6.0
Summary: UNKNOWN
Home-page: https://github.com/relaxdiego/aircraft
Author: Mark S. Maglana
Author-email: mmaglana@gmail.com
License: UNKNOWN
Platform: UNKNOWN
Classifier: Programming Language :: Python :: 3
Classifier: License :: OSI Approved :: Apache Software License
Classifier: Operating System :: POSIX :: Linux
Requires-Python: ~=3.6
